{
  "generated_at": "2025-12-07T18:20:56.496171+08:00",
  "total_titles_processed": 1051,
  "failed_sources": [],
  "trends": [
    {
      "keyword_group": "# ===== 焦点人物 ===== 特朗普 马斯克 高市早苗",
      "match_count": 31,
      "titles": [
        {
          "title": "戴尔创始人捐 62.5 亿美元，为全美 2500 万儿童开启「特朗普账户」储蓄计划，对此你怎么看？",
          "url": "https://www.zhihu.com/question/1979570545172423754",
          "source": "知乎",
          "ranks": [
            8,
            4,
            3
          ],
          "is_new": false,
          "appearance_count": 10,
          "time_info": "[00时26分 ~ 07时20分]"
        },
        {
          "title": "马斯克：欧盟应当被废除，主权应归还给各个国家，这样政府就能更好地代表其民众了。",
          "url": "https://flash.jin10.com/detail/20251206220812258800",
          "source": "金十数据",
          "ranks": [
            4,
            24
          ],
          "is_new": false,
          "appearance_count": 9,
          "time_info": "[00时26分 ~ 09时54分]"
        },
        {
          "title": "高市早苗被曝自身难保",
          "url": "https://s.weibo.com/weibo?q=%23%E9%AB%98%E5%B8%82%E6%97%A9%E8%8B%97%E8%A2%AB%E6%9B%9D%E8%87%AA%E8%BA%AB%E9%9A%BE%E4%BF%9D%23&t=31&band_rank=2&Refer=top",
          "source": "微博",
          "ranks": [
            2,
            7,
            18,
            16,
            15,
            8
          ],
          "is_new": false,
          "appearance_count": 10,
          "time_info": "[00时26分 ~ 07时20分]"
        },
        {
          "title": "明年起，特朗普生日当天美国国家公园免费入园，外国人除外",
          "url": "https://news.ifeng.com/c/8os5vGpW9R1",
          "source": "凤凰网",
          "ranks": [
            9
          ],
          "is_new": false,
          "appearance_count": 10,
          "time_info": "[00时26分 ~ 07时20分]"
        },
        {
          "title": "马斯克称欧盟应该被废除",
          "url": "https://wallstreetcn.com/livenews/3016320",
          "source": "华尔街见闻-快讯",
          "ranks": [
            7,
            12,
            20,
            24,
            30
          ],
          "is_new": false,
          "appearance_count": 12,
          "time_info": "[00时26分 ~ 13时20分]"
        },
        {
          "title": "特朗普获“国际足联和平奖”，迫不及待给自己戴奖牌",
          "url": "https://v.ifeng.com/c/8oreqqskdgg",
          "source": "凤凰网",
          "ranks": [
            10
          ],
          "is_new": false,
          "appearance_count": 11,
          "time_info": "[00时26分 ~ 09时54分]"
        },
        {
          "title": "特朗普最终果然如媒体和大众判断的那样，顺利获得国际足联新设立的和平奖，对此你怎么看？",
          "url": "https://www.zhihu.com/question/1979961793922167510",
          "source": "知乎",
          "ranks": [
            16,
            15
          ],
          "is_new": false,
          "appearance_count": 10,
          "time_info": "[00时26分 ~ 07时20分]"
        },
        {
          "title": "马斯克回应“SpaceX冲击8000亿美元估值”传闻",
          "url": "https://wallstreetcn.com/livenews/3016330",
          "source": "华尔街见闻-快讯",
          "ranks": [
            5,
            13,
            17,
            23,
            24,
            25,
            26,
            29,
            30
          ],
          "is_new": false,
          "appearance_count": 9,
          "time_info": "[09时54分 ~ 18时20分]"
        },
        {
          "title": "马斯克回应“SpaceX冲击8000亿美元估值”传闻",
          "url": "https://www.cls.cn/detail/2221851",
          "source": "财联社热门",
          "ranks": [
            13,
            12,
            11,
            10,
            9
          ],
          "is_new": false,
          "appearance_count": 9,
          "time_info": "[11时38分 ~ 18时20分]"
        },
        {
          "title": "高市早苗被曝自身难保，或提前下台",
          "url": "https://news.ifeng.com/c/8otJRMgw24C",
          "source": "凤凰网",
          "ranks": [
            1
          ],
          "is_new": false,
          "appearance_count": 3,
          "time_info": "[16时27分 ~ 18时20分]"
        },
        {
          "title": "日本学者：高市早苗应被停职处理",
          "url": "https://v.ifeng.com/c/8osF3a6FiWg",
          "source": "凤凰网",
          "ranks": [
            2
          ],
          "is_new": false,
          "appearance_count": 3,
          "time_info": "[16时27分 ~ 18时20分]"
        },
        {
          "title": "美国发生特大诈骗案 特朗普怒批",
          "url": "https://www.baidu.com/s?wd=%E7%BE%8E%E5%9B%BD%E5%8F%91%E7%94%9F%E7%89%B9%E5%A4%A7%E8%AF%88%E9%AA%97%E6%A1%88+%E7%89%B9%E6%9C%97%E6%99%AE%E6%80%92%E6%89%B9",
          "source": "百度热搜",
          "ranks": [
            27,
            5,
            10,
            15,
            14
          ],
          "is_new": false,
          "appearance_count": 6,
          "time_info": "[11时38分 ~ 15时21分]"
        },
        {
          "title": "马斯克：Grok 4.20将在3至4周内发布。",
          "url": "https://wallstreetcn.com/livenews/3016385",
          "source": "华尔街见闻-快讯",
          "ranks": [
            2,
            3
          ],
          "is_new": false,
          "appearance_count": 2,
          "time_info": "[17时21分 ~ 18时20分]"
        },
        {
          "title": "特朗普签署行政令调查外资企业食品反竞争行为",
          "url": "https://flash.jin10.com/detail/20251207124750348800",
          "source": "金十数据",
          "ranks": [
            1,
            6,
            11,
            18,
            22
          ],
          "is_new": false,
          "appearance_count": 5,
          "time_info": "[13时20分 ~ 17时21分]"
        },
        {
          "title": "金十数据整理：特朗普过去24小时都忙了什么？（2025-12-07）",
          "url": "https://flash.jin10.com/detail/20251207175156547800",
          "source": "金十数据",
          "ranks": [
            1
          ],
          "is_new": true,
          "appearance_count": 1,
          "time_info": "18时20分"
        },
        {
          "title": "美防长：特朗普政府将“把国家实际利益放在首位”",
          "url": "https://flash.jin10.com/detail/20251207122838853800",
          "source": "金十数据",
          "ranks": [
            4,
            9,
            14,
            21,
            25
          ],
          "is_new": false,
          "appearance_count": 5,
          "time_info": "[13时20分 ~ 17时21分]"
        },
        {
          "title": "“马斯克专属估值”？SpaceX以1/6的特斯拉收入，超过特斯拉一半的估值，考虑2026年IPO",
          "url": "https://wallstreetcn.com/articles/3760842",
          "source": "华尔街见闻",
          "ranks": [
            9,
            7,
            6
          ],
          "is_new": false,
          "appearance_count": 5,
          "time_info": "[09时54分 ~ 14时31分]"
        },
        {
          "title": "马斯克：有关SpaceX以8000亿美元估值进行融资的传闻不准确",
          "url": "https://flash.jin10.com/detail/20251207091937087800",
          "source": "金十数据",
          "ranks": [
            1,
            15,
            21
          ],
          "is_new": false,
          "appearance_count": 3,
          "time_info": "[09时54分 ~ 12时34分]"
        },
        {
          "title": "马斯克：Grok 4.20将在3至4周内发布。",
          "url": "https://flash.jin10.com/detail/20251207164105417800",
          "source": "金十数据",
          "ranks": [
            1,
            9
          ],
          "is_new": false,
          "appearance_count": 2,
          "time_info": "[17时21分 ~ 18时20分]"
        },
        {
          "title": "马斯克旗下 SpaceX 考虑 2026 年 IPO，最新估值达 8 千亿美元，较今年 7 月翻倍，对此你怎么看？",
          "url": "https://www.zhihu.com/question/1980618656774894195",
          "source": "知乎",
          "ranks": [
            6,
            9,
            14
          ],
          "is_new": false,
          "appearance_count": 3,
          "time_info": "[00时26分 ~ 02时29分]"
        },
        {
          "title": "马斯克：有很多媒体报道称SpaceX正以8000亿美元的估值进行融资，这一说法并不准确。",
          "url": "https://flash.jin10.com/detail/20251207083014951800",
          "source": "金十数据",
          "ranks": [
            7,
            21,
            27
          ],
          "is_new": false,
          "appearance_count": 3,
          "time_info": "[09时54分 ~ 12时34分]"
        },
        {
          "title": "马斯克公开呼吁：废除欧盟",
          "url": "https://www.baidu.com/s?wd=%E9%A9%AC%E6%96%AF%E5%85%8B%E5%85%AC%E5%BC%80%E5%91%BC%E5%90%81%EF%BC%9A%E5%BA%9F%E9%99%A4%E6%AC%A7%E7%9B%9F",
          "source": "百度热搜",
          "ranks": [
            23,
            14,
            16
          ],
          "is_new": false,
          "appearance_count": 3,
          "time_info": "[16时27分 ~ 18时20分]"
        },
        {
          "title": "年终总结特朗普重返白宫",
          "url": "https://search.bilibili.com/all?keyword=%E5%B9%B4%E7%BB%88%E6%80%BB%E7%BB%93%E7%89%B9%E6%9C%97%E6%99%AE%E9%87%8D%E8%BF%94%E7%99%BD%E5%AE%AB",
          "source": "bilibili 热搜",
          "ranks": [
            8
          ],
          "is_new": false,
          "appearance_count": 2,
          "time_info": "[15时20分 ~ 15时21分]"
        },
        {
          "title": "高市早苗欲成立日本版中情局",
          "url": "https://www.douyin.com/hot/2328057",
          "source": "抖音",
          "ranks": [
            29,
            7
          ],
          "is_new": false,
          "appearance_count": 2,
          "time_info": "[06时20分 ~ 07时20分]"
        },
        {
          "title": "日本籍八路军老战士后代批高市早苗",
          "url": "https://www.toutiao.com/trending/7581015240683552795/",
          "source": "今日头条",
          "ranks": [
            8
          ],
          "is_new": true,
          "appearance_count": 1,
          "time_info": "18时20分"
        },
        {
          "title": "马斯克抨击欧盟对社交媒体平台X巨额罚款",
          "url": "https://news.ifeng.com/c/8ot6IrYZIZ4",
          "source": "凤凰网",
          "ranks": [
            12
          ],
          "is_new": false,
          "appearance_count": 1,
          "time_info": "16时27分"
        },
        {
          "title": "特朗普或将给高市早苗放权",
          "url": "https://s.weibo.com/weibo?q=%23%E7%89%B9%E6%9C%97%E6%99%AE%E6%88%96%E5%B0%86%E7%BB%99%E9%AB%98%E5%B8%82%E6%97%A9%E8%8B%97%E6%94%BE%E6%9D%83%23&t=31&band_rank=14&Refer=top",
          "source": "微博",
          "ranks": [
            14
          ],
          "is_new": false,
          "appearance_count": 1,
          "time_info": "09时54分"
        },
        {
          "title": "美国家公园免票政策调整：增特朗普生日，取消马丁・路德・金纪念日",
          "url": "https://m.thepaper.cn/newsDetail_forward_32124875",
          "source": "澎湃新闻",
          "ranks": [
            18
          ],
          "is_new": true,
          "appearance_count": 1,
          "time_info": "18时20分"
        },
        {
          "title": "特朗普称其主持典礼会比吉米做得更好",
          "url": "https://www.toutiao.com/trending/7580414475011047451/",
          "source": "今日头条",
          "ranks": [
            21
          ],
          "is_new": false,
          "appearance_count": 1,
          "time_info": "13时20分"
        },
        {
          "title": "特朗普威胁封锁委领空 马杜罗咋办",
          "url": "https://www.toutiao.com/trending/7581027611489340991/",
          "source": "今日头条",
          "ranks": [
            27
          ],
          "is_new": true,
          "appearance_count": 1,
          "time_info": "18时20分"
        },
        {
          "title": "周锡玮：高市早苗从没走过正确台阶",
          "url": "https://www.toutiao.com/trending/7580362626229764106/",
          "source": "今日头条",
          "ranks": [
            30
          ],
          "is_new": true,
          "appearance_count": 1,
          "time_info": "18时20分"
        }
      ]
    },
    {
      "keyword_group": "# ===== 好物分享 ===== 书籍 故事 人物 历史",
      "match_count": 6,
      "titles": [
        {
          "title": "监事会正退出A股历史舞台，42家上市券商已进行监事会撤销",
          "url": "https://www.cls.cn/detail/2221687",
          "source": "财联社热门",
          "ranks": [
            1,
            2,
            3
          ],
          "is_new": false,
          "appearance_count": 20,
          "time_info": "[00时26分 ~ 18时20分]"
        },
        {
          "title": "深圳机场国际及地区客运航线数量恢复至历史峰值水平",
          "url": "https://wallstreetcn.com/livenews/3016319",
          "source": "华尔街见闻-快讯",
          "ranks": [
            8,
            13,
            21,
            25
          ],
          "is_new": false,
          "appearance_count": 11,
          "time_info": "[00时26分 ~ 12时34分]"
        },
        {
          "title": "深圳机场国际及地区客运航线数量恢复至历史峰值水平",
          "url": "https://flash.jin10.com/detail/20251206213713871800",
          "source": "金十数据",
          "ranks": [
            9,
            29
          ],
          "is_new": false,
          "appearance_count": 9,
          "time_info": "[00时26分 ~ 09时54分]"
        },
        {
          "title": "约书亚万KO夺冠!创亚洲历史",
          "url": "https://tieba.baidu.com/hottopic/browse/hottopic?topic_id=28347780&amp;topic_name=%E7%BA%A6%E4%B9%A6%E4%BA%9A%E4%B8%87KO%E5%A4%BA%E5%86%A0%21%E5%88%9B%E4%BA%9A%E6%B4%B2%E5%8E%86%E5%8F%B2",
          "source": "贴吧",
          "ranks": [
            30,
            7,
            9
          ],
          "is_new": false,
          "appearance_count": 5,
          "time_info": "[15时20分 ~ 18时20分]"
        },
        {
          "title": "国家药监局：今年我国批准创新药数量已创历史新高",
          "url": "https://flash.jin10.com/detail/20251207100617234800",
          "source": "金十数据",
          "ranks": [
            10,
            16,
            26
          ],
          "is_new": false,
          "appearance_count": 3,
          "time_info": "[11时38分 ~ 13时20分]"
        },
        {
          "title": "哈登历史得分榜第十位",
          "url": "https://search.bilibili.com/all?keyword=%E5%93%88%E7%99%BB%E5%8E%86%E5%8F%B2%E5%BE%97%E5%88%86%E6%A6%9C%E7%AC%AC%E5%8D%81%E4%BD%8D",
          "source": "bilibili 热搜",
          "ranks": [
            14
          ],
          "is_new": false,
          "appearance_count": 2,
          "time_info": "[15时20分 ~ 15时21分]"
        }
      ]
    },
    {
      "keyword_group": "# ===== 社交观察 ===== 爱好 兴趣 职场",
      "match_count": 1,
      "titles": [
        {
          "title": "兴趣消费释放文旅新动能",
          "url": "https://www.douyin.com/hot/2328577",
          "source": "抖音",
          "ranks": [
            3
          ],
          "is_new": false,
          "appearance_count": 12,
          "time_info": "[00时26分 ~ 11时38分]"
        }
      ]
    }
  ],
  "report_image_url": "https://news.yoos.top/img/news.jpg"
}